lib_x17_fintech-2.1.7.dist-info/licenses/LICENSE
xfintech/__init__.py
xfintech/data/__init__.py
xfintech/data/common/__init__.py
xfintech/data/common/cache.py
xfintech/data/common/coolant.py
xfintech/data/common/metric.py
xfintech/data/common/paginate.py
xfintech/data/common/params.py
xfintech/data/common/retry.py
xfintech/data/common/tests/__init__.py
xfintech/data/common/tests/test_class_cache_all.py
xfintech/data/common/tests/test_class_coolant_all.py
xfintech/data/common/tests/test_class_metric_all.py
xfintech/data/common/tests/test_class_paginate_all.py
xfintech/data/common/tests/test_class_params_all.py
xfintech/data/common/tests/test_class_retry_all.py
xfintech/data/job/__init__.py
xfintech/data/job/errors.py
xfintech/data/job/house.py
xfintech/data/job/job.py
xfintech/data/job/joblike.py
xfintech/data/job/tests/__init__.py
xfintech/data/job/tests/test_class_errors_all.py
xfintech/data/job/tests/test_class_house_all.py
xfintech/data/job/tests/test_class_job_all.py
xfintech/data/job/tests/test_class_joblike_all.py
xfintech/data/relay/__init__.py
xfintech/data/relay/client.py
xfintech/data/relay/clientlike.py
xfintech/data/relay/tests/test_class_relayclient_all.py
xfintech/data/relay/tests/test_class_relayclientlike_all.py
xfintech/data/source/__init__.py
xfintech/data/source/baostock/__init__.py
xfintech/data/source/baostock/job/__init__.py
xfintech/data/source/baostock/job/job.py
xfintech/data/source/baostock/job/tests/__init__.py
xfintech/data/source/baostock/job/tests/test_class_baostockjob_all.py
xfintech/data/source/baostock/session/__init__.py
xfintech/data/source/baostock/session/relay.py
xfintech/data/source/baostock/session/session.py
xfintech/data/source/baostock/session/tests/__init__.py
xfintech/data/source/baostock/session/tests/test_class_relay_all.py
xfintech/data/source/baostock/session/tests/test_class_session_all.py
xfintech/data/source/baostock/stock/__init__.py
xfintech/data/source/baostock/stock/hs300stock/__init__.py
xfintech/data/source/baostock/stock/hs300stock/constant.py
lib_x17_fintech-2.1.7.dist-info/METADATA
lib_x17_fintech-2.1.7.dist-info/WHEEL
lib_x17_fintech-2.1.7.dist-info/top_level.txt
lib_x17_fintech-2.1.7.dist-info/RECORD
