Metadata-Version: 2.4
Name: lib-x17-fintech
Version: 2.1.7
Summary: fintech module for x17 echosystem
Author-email: Xing Xing <x.xing.work@gmail.com>
License-Expression: MIT
Requires-Python: >=3.11
License-File: LICENSE
Requires-Dist: pyarrow>=21.0.0
Requires-Dist: pytz>=2025.0
Requires-Dist: backoff>=2.0
Requires-Dist: tushare>=1.4.0
Requires-Dist: baostock>=0.8.0
Requires-Dist: pandas>=2.2.2
Requires-Dist: numpy>=1.25.2
Requires-Dist: boto3>=1.17.0
Provides-Extra: dev
Requires-Dist: pytest>=8.3; extra == "dev"
Requires-Dist: pytest-cov>=6.0; extra == "dev"
Requires-Dist: pytest-benchmark; extra == "dev"
Requires-Dist: ruff>=0.13; extra == "dev"
Requires-Dist: setuptools; extra == "dev"
Requires-Dist: wheel; extra == "dev"
Requires-Dist: twine; extra == "dev"
Requires-Dist: build; extra == "dev"
Dynamic: license-file
